*.cpython-38-darwin.so
cjoin.cpython-38-darwin.so
pyarrow_ops.cpython-38-darwin.so
pyarrow_ops/__init__.py
pyarrow_ops/cjoin.c
pyarrow_ops/cjoin.cpython-38-darwin.so
pyarrow_ops/cjoin.pyx
pyarrow_ops/group.py
pyarrow_ops/helpers.py
pyarrow_ops/join.py
pyarrow_ops/jsons.py
pyarrow_ops/ml.py
pyarrow_ops/ops.py
pyarrow_ops/table.py
pyarrow_ops-0.0.8.dist-info/LICENSE
pyarrow_ops-0.0.8.dist-info/METADATA
pyarrow_ops-0.0.8.dist-info/WHEEL
pyarrow_ops-0.0.8.dist-info/top_level.txt
pyarrow_ops-0.0.8.dist-info/RECORD
