Metadata-Version: 2.1
Name: pyarrow-ops
Version: 0.0.8
Summary: Useful data crunching tools for pyarrow
Home-page: https://github.com/TomScheffers/pyarrow_ops
Author: Tom Scheffers
Author-email: tom@youngbulls.nl 
License: APACHE
Download-URL: https://pypi.org/project/pyarrow-ops/
Keywords: arrow,pyarrow,data
Platform: UNKNOWN
Requires-Dist: numpy (>=1.19.2)
Requires-Dist: pyarrow (>=3.0)
